specfem/__init__.py
specfem/adjoint.py
specfem/forward.py
specfem/mesh.py
specfem/shared.py
specfem/typing.py
specfem-0.0.2.dist-info/LICENSE
specfem-0.0.2.dist-info/METADATA
specfem-0.0.2.dist-info/WHEEL
specfem-0.0.2.dist-info/top_level.txt
specfem-0.0.2.dist-info/RECORD
