Metadata-Version: 2.1
Name: specfem
Version: 0.0.2
Summary: Python interface for SPECFEM++.
Home-page: https://github.com/icui/pyspecfem
Author: Congyue Cui
Author-email: ccui@princeton.edu
Maintainer-email: ccui@princeton.edu
Keywords: Workflow,Cluster,MPI
Classifier: Programming Language :: Python :: 3
Classifier: License :: OSI Approved :: MIT License
Classifier: Operating System :: OS Independent
Requires-Python: >=3.11
License-File: LICENSE
Provides-Extra: docs
Requires-Dist: sphinx ; extra == 'docs'
Requires-Dist: furo ; extra == 'docs'
Requires-Dist: myst-parser ; extra == 'docs'
Provides-Extra: mpi
Requires-Dist: mpi4py ; extra == 'mpi'
